CHANGELOG.txt
LICENCE.txt
MANIFEST.in
README.txt
setup.py
ap9boy_isa.egg-info/PKG-INFO
ap9boy_isa.egg-info/SOURCES.txt
ap9boy_isa.egg-info/dependency_links.txt
ap9boy_isa.egg-info/top_level.txt
joshbasiccalculator/__init__.py