Metadata-Version: 1.1
Name: ap9boy-isa
Version: 0.0.1
Summary: A very cool person
Home-page: UNKNOWN
Author: Pavel Andrei
Author-email: andrew8pa@gmail.com
License: MIT
Keywords: human
Platform: UNKNOWN
Classifier: Development Status :: 5 - Production/Stable
Classifier: Intended Audience :: Education
Classifier: Operating System :: Microsoft :: Windows :: Windows 10
Classifier: License :: OSI Approved :: MIT License
Classifier: Programming Language :: Python :: 3
